{"instrument": {"id": 17631803, "name": "Global X Cybersecurity UCITS ETF USD Accumulating", "ticker": "BUG", "kind": "etf", "currency": "EUR", "country": "DE", "tz": "Europe/Berlin", "slug": "global-x-cybersecurity-ucits-bug-xeta", "owners": 559}, "asOf": "2026-06-05", "momentum": {"m3": 43.8, "m12": 0.5}, "daysAxis": ["Mon", "Tue", "Wed", "Thu", "Fri"], "hoursAxis": [], "monthsAxis": ["Jan", "Feb", "Mar", "Apr", "May", "Jun", "Jul", "Aug", "Sep", "Oct", "Nov", "Dec"], "earnings": null, "tf": {"1Y": {"sampleSize": 252, "intradayDays": 0, "weekday": [{"key": "Mon", "ret": 0.739, "winRate": 75, "volume": 99, "vol": 2.2, "n": 51, "t": 2.4, "edge": 87}, {"key": "Tue", "ret": -0.259, "winRate": 46, "volume": 96, "vol": 1.58, "n": 52, "t": -1.18, "edge": 11}, {"key": "Wed", "ret": -0.116, "winRate": 45, "volume": 98, "vol": 1.52, "n": 51, "t": -0.55, "edge": 28}, {"key": "Thu", "ret": 0.035, "winRate": 47, "volume": 96, "vol": 2.16, "n": 51, "t": 0.12, "edge": 11}, {"key": "Fri", "ret": -0.317, "winRate": 45, "volume": 100, "vol": 1.87, "n": 47, "t": -1.16, "edge": 18}], "hour": null, "month": [{"key": "Jan", "ret": -0.364, "winRate": 43, "volume": 86, "vol": 1.66, "n": 21, "t": -1.0, "edge": 22}, {"key": "Feb", "ret": -0.645, "winRate": 40, "volume": 92, "vol": 2.84, "n": 20, "t": -1.02, "edge": 8}, {"key": "Mar", "ret": 0.101, "winRate": 43, "volume": 87, "vol": 1.64, "n": 21, "t": 0.28, "edge": 34}, {"key": "Apr", "ret": 0.281, "winRate": 70, "volume": 93, "vol": 2.51, "n": 20, "t": 0.5, "edge": 51}, {"key": "May", "ret": 1.486, "winRate": 85, "volume": 100, "vol": 2.49, "n": 20, "t": 2.66, "edge": 94}, {"key": "Jun", "ret": 0.231, "winRate": 57, "volume": 84, "vol": 2.2, "n": 23, "t": 0.5, "edge": 37}, {"key": "Jul", "ret": -0.112, "winRate": 43, "volume": 80, "vol": 1.41, "n": 23, "t": -0.38, "edge": 24}, {"key": "Aug", "ret": -0.213, "winRate": 48, "volume": 83, "vol": 1.5, "n": 21, "t": -0.65, "edge": 27}, {"key": "Sep", "ret": 0.119, "winRate": 59, "volume": 80, "vol": 1.08, "n": 22, "t": 0.52, "edge": 42}, {"key": "Oct", "ret": -0.033, "winRate": 59, "volume": 82, "vol": 1.74, "n": 22, "t": -0.09, "edge": 34}, {"key": "Nov", "ret": -0.443, "winRate": 30, "volume": 85, "vol": 1.23, "n": 20, "t": -1.61, "edge": 15}, {"key": "Dec", "ret": -0.161, "winRate": 42, "volume": 83, "vol": 0.91, "n": 19, "t": -0.77, "edge": 30}], "matrix": null, "recommendation": {"verdict": "BUY", "confidence": 78, "bestWindow": {"day": "Mon", "hour": null, "edge": 87}, "worstWindow": {"day": "Tue", "hour": null, "edge": 11}, "earningsSoon": false}}, "3Y": {"sampleSize": 756, "intradayDays": 0, "weekday": [{"key": "Mon", "ret": 0.461, "winRate": 63, "volume": 98, "vol": 1.62, "n": 151, "t": 3.5, "edge": 81}, {"key": "Tue", "ret": 0.015, "winRate": 52, "volume": 98, "vol": 1.41, "n": 153, "t": 0.14, "edge": 31}, {"key": "Wed", "ret": -0.062, "winRate": 48, "volume": 98, "vol": 1.6, "n": 151, "t": -0.47, "edge": 8}, {"key": "Thu", "ret": 0.033, "winRate": 52, "volume": 99, "vol": 1.8, "n": 152, "t": 0.23, "edge": 24}, {"key": "Fri", "ret": -0.153, "winRate": 48, "volume": 100, "vol": 1.55, "n": 149, "t": -1.21, "edge": 21}], "hour": null, "month": [{"key": "Jan", "ret": 0.075, "winRate": 51, "volume": 95, "vol": 1.42, "n": 65, "t": 0.43, "edge": 49}, {"key": "Feb", "ret": -0.227, "winRate": 51, "volume": 100, "vol": 2.15, "n": 61, "t": -0.82, "edge": 22}, {"key": "Mar", "ret": -0.13, "winRate": 47, "volume": 99, "vol": 1.6, "n": 62, "t": -0.64, "edge": 26}, {"key": "Apr", "ret": 0.035, "winRate": 59, "volume": 97, "vol": 2.19, "n": 61, "t": 0.12, "edge": 56}, {"key": "May", "ret": 0.466, "winRate": 57, "volume": 98, "vol": 1.87, "n": 63, "t": 1.98, "edge": 89}, {"key": "Jun", "ret": 0.273, "winRate": 56, "volume": 93, "vol": 1.62, "n": 61, "t": 1.32, "edge": 70}, {"key": "Jul", "ret": -0.007, "winRate": 51, "volume": 89, "vol": 1.25, "n": 67, "t": -0.05, "edge": 38}, {"key": "Aug", "ret": -0.032, "winRate": 53, "volume": 94, "vol": 1.59, "n": 66, "t": -0.16, "edge": 42}, {"key": "Sep", "ret": 0.034, "winRate": 55, "volume": 86, "vol": 1.1, "n": 64, "t": 0.25, "edge": 49}, {"key": "Oct", "ret": -0.056, "winRate": 49, "volume": 88, "vol": 1.48, "n": 67, "t": -0.31, "edge": 24}, {"key": "Nov", "ret": 0.239, "winRate": 56, "volume": 91, "vol": 1.53, "n": 63, "t": 1.24, "edge": 66}, {"key": "Dec", "ret": 0.049, "winRate": 46, "volume": 93, "vol": 1.04, "n": 56, "t": 0.35, "edge": 38}], "matrix": null, "recommendation": {"verdict": "BUY", "confidence": 79, "bestWindow": {"day": "Mon", "hour": null, "edge": 81}, "worstWindow": {"day": "Wed", "hour": null, "edge": 8}, "earningsSoon": false}}, "5Y": {"sampleSize": 1153, "intradayDays": 0, "weekday": [{"key": "Mon", "ret": 0.225, "winRate": 59, "volume": 99, "vol": 1.82, "n": 228, "t": 1.87, "edge": 88}, {"key": "Tue", "ret": 0.043, "winRate": 50, "volume": 98, "vol": 1.66, "n": 234, "t": 0.39, "edge": 45}, {"key": "Wed", "ret": -0.025, "winRate": 50, "volume": 98, "vol": 1.69, "n": 232, "t": -0.22, "edge": 33}, {"key": "Thu", "ret": 0.013, "winRate": 53, "volume": 100, "vol": 1.9, "n": 233, "t": 0.11, "edge": 48}, {"key": "Fri", "ret": -0.152, "winRate": 46, "volume": 99, "vol": 1.69, "n": 226, "t": -1.35, "edge": 16}], "hour": null, "month": [{"key": "Jan", "ret": 0.0, "winRate": 51, "volume": 96, "vol": 1.95, "n": 108, "t": 0.0, "edge": 37}, {"key": "Feb", "ret": 0.006, "winRate": 51, "volume": 100, "vol": 2.1, "n": 101, "t": 0.03, "edge": 40}, {"key": "Mar", "ret": -0.024, "winRate": 52, "volume": 98, "vol": 1.63, "n": 108, "t": -0.15, "edge": 48}, {"key": "Apr", "ret": -0.094, "winRate": 53, "volume": 96, "vol": 1.91, "n": 98, "t": -0.49, "edge": 33}, {"key": "May", "ret": 0.298, "winRate": 55, "volume": 99, "vol": 1.91, "n": 107, "t": 1.61, "edge": 94}, {"key": "Jun", "ret": 0.142, "winRate": 54, "volume": 96, "vol": 1.71, "n": 89, "t": 0.78, "edge": 72}, {"key": "Jul", "ret": 0.046, "winRate": 50, "volume": 87, "vol": 1.42, "n": 88, "t": 0.3, "edge": 40}, {"key": "Aug", "ret": 0.066, "winRate": 55, "volume": 91, "vol": 1.76, "n": 89, "t": 0.36, "edge": 57}, {"key": "Sep", "ret": -0.054, "winRate": 52, "volume": 89, "vol": 1.38, "n": 86, "t": -0.37, "edge": 38}, {"key": "Oct", "ret": -0.012, "winRate": 49, "volume": 88, "vol": 1.66, "n": 88, "t": -0.07, "edge": 25}, {"key": "Nov", "ret": -0.092, "winRate": 49, "volume": 91, "vol": 1.94, "n": 93, "t": -0.46, "edge": 11}, {"key": "Dec", "ret": -0.048, "winRate": 46, "volume": 92, "vol": 1.43, "n": 98, "t": -0.34, "edge": 21}], "matrix": null, "recommendation": {"verdict": "BUY", "confidence": 78, "bestWindow": {"day": "Mon", "hour": null, "edge": 88}, "worstWindow": {"day": "Fri", "hour": null, "edge": 16}, "earningsSoon": false}}}}