{"instrument": {"id": 17975090, "name": "Xtrackers MSCI Global Clean Water & Sanitation UCITS ETF 1C", "ticker": "XDG6", "kind": "etf", "currency": "EUR", "country": "DE", "tz": "Europe/Berlin", "slug": "xtrackers-msci-global-clean-xdg6-xeta", "owners": 72}, "asOf": "2026-07-17", "momentum": {"m3": 5.2, "m12": 6.3}, "daysAxis": ["Mon", "Tue", "Wed", "Thu", "Fri"], "hoursAxis": [], "monthsAxis": ["Jan", "Feb", "Mar", "Apr", "May", "Jun", "Jul", "Aug", "Sep", "Oct", "Nov", "Dec"], "earnings": null, "tf": {"1Y": {"sampleSize": 252, "intradayDays": 0, "weekday": [{"key": "Mon", "ret": -0.314, "winRate": 45, "volume": 98, "vol": 2.09, "n": 51, "t": -1.07, "edge": 14}, {"key": "Tue", "ret": -0.099, "winRate": 46, "volume": 92, "vol": 0.61, "n": 52, "t": -1.17, "edge": 36}, {"key": "Wed", "ret": 0.195, "winRate": 72, "volume": 91, "vol": 0.61, "n": 50, "t": 2.25, "edge": 86}, {"key": "Thu", "ret": 0.256, "winRate": 61, "volume": 91, "vol": 0.96, "n": 51, "t": 1.9, "edge": 77}, {"key": "Fri", "ret": 0.159, "winRate": 40, "volume": 100, "vol": 2.57, "n": 48, "t": 0.43, "edge": 50}], "hour": null, "month": [{"key": "Jan", "ret": -0.014, "winRate": 52, "volume": 100, "vol": 0.74, "n": 21, "t": -0.09, "edge": 62}, {"key": "Feb", "ret": 0.268, "winRate": 65, "volume": 94, "vol": 0.64, "n": 20, "t": 1.88, "edge": 88}, {"key": "Mar", "ret": -0.281, "winRate": 48, "volume": 100, "vol": 0.84, "n": 21, "t": -1.54, "edge": 34}, {"key": "Apr", "ret": -0.022, "winRate": 40, "volume": 87, "vol": 0.69, "n": 20, "t": -0.14, "edge": 35}, {"key": "May", "ret": -0.007, "winRate": 35, "volume": 94, "vol": 1.64, "n": 20, "t": -0.02, "edge": 39}, {"key": "Jun", "ret": 0.167, "winRate": 55, "volume": 93, "vol": 0.8, "n": 22, "t": 0.98, "edge": 70}, {"key": "Jul", "ret": 0.213, "winRate": 83, "volume": 98, "vol": 0.58, "n": 23, "t": 1.78, "edge": 100}, {"key": "Aug", "ret": 0.045, "winRate": 57, "volume": 95, "vol": 0.61, "n": 21, "t": 0.34, "edge": 64}, {"key": "Sep", "ret": -0.05, "winRate": 36, "volume": 97, "vol": 0.51, "n": 22, "t": -0.46, "edge": 44}, {"key": "Oct", "ret": 0.088, "winRate": 57, "volume": 90, "vol": 4.61, "n": 23, "t": 0.09, "edge": 43}, {"key": "Nov", "ret": 0.011, "winRate": 65, "volume": 89, "vol": 0.6, "n": 20, "t": 0.08, "edge": 58}, {"key": "Dec", "ret": 0.004, "winRate": 37, "volume": 95, "vol": 0.49, "n": 19, "t": 0.03, "edge": 47}], "matrix": null, "recommendation": {"verdict": "BUY", "confidence": 60, "bestWindow": {"day": "Wed", "hour": null, "edge": 86}, "worstWindow": {"day": "Mon", "hour": null, "edge": 14}, "earningsSoon": false}}, "3Y": {"sampleSize": 756, "intradayDays": 0, "weekday": [{"key": "Mon", "ret": -0.099, "winRate": 50, "volume": 99, "vol": 1.34, "n": 151, "t": -0.91, "edge": 19}, {"key": "Tue", "ret": -0.057, "winRate": 48, "volume": 97, "vol": 0.67, "n": 153, "t": -1.05, "edge": 26}, {"key": "Wed", "ret": 0.006, "winRate": 56, "volume": 94, "vol": 0.73, "n": 151, "t": 0.1, "edge": 59}, {"key": "Thu", "ret": 0.181, "winRate": 56, "volume": 96, "vol": 0.85, "n": 152, "t": 2.64, "edge": 93}, {"key": "Fri", "ret": 0.033, "winRate": 48, "volume": 100, "vol": 1.58, "n": 149, "t": 0.26, "edge": 33}], "hour": null, "month": [{"key": "Jan", "ret": 0.038, "winRate": 51, "volume": 100, "vol": 0.71, "n": 65, "t": 0.43, "edge": 63}, {"key": "Feb", "ret": 0.136, "winRate": 59, "volume": 98, "vol": 0.55, "n": 61, "t": 1.94, "edge": 92}, {"key": "Mar", "ret": -0.086, "winRate": 52, "volume": 99, "vol": 0.74, "n": 62, "t": -0.91, "edge": 38}, {"key": "Apr", "ret": -0.08, "winRate": 44, "volume": 98, "vol": 1.21, "n": 61, "t": -0.52, "edge": 24}, {"key": "May", "ret": 0.012, "winRate": 48, "volume": 97, "vol": 1.04, "n": 63, "t": 0.09, "edge": 48}, {"key": "Jun", "ret": -0.022, "winRate": 41, "volume": 97, "vol": 0.64, "n": 63, "t": -0.27, "edge": 35}, {"key": "Jul", "ret": 0.122, "winRate": 67, "volume": 99, "vol": 0.65, "n": 64, "t": 1.51, "edge": 99}, {"key": "Aug", "ret": -0.015, "winRate": 59, "volume": 91, "vol": 0.7, "n": 66, "t": -0.17, "edge": 51}, {"key": "Sep", "ret": -0.019, "winRate": 45, "volume": 86, "vol": 0.58, "n": 64, "t": -0.26, "edge": 27}, {"key": "Oct", "ret": -0.077, "winRate": 49, "volume": 92, "vol": 2.73, "n": 68, "t": -0.23, "edge": 10}, {"key": "Nov", "ret": 0.16, "winRate": 59, "volume": 91, "vol": 0.69, "n": 63, "t": 1.83, "edge": 86}, {"key": "Dec", "ret": -0.011, "winRate": 45, "volume": 94, "vol": 0.56, "n": 56, "t": -0.15, "edge": 39}], "matrix": null, "recommendation": {"verdict": "BUY", "confidence": 59, "bestWindow": {"day": "Thu", "hour": null, "edge": 93}, "worstWindow": {"day": "Mon", "hour": null, "edge": 19}, "earningsSoon": false}}, "5Y": {"sampleSize": 885, "intradayDays": 0, "weekday": [{"key": "Mon", "ret": -0.09, "winRate": 50, "volume": 100, "vol": 1.26, "n": 175, "t": -0.94, "edge": 23}, {"key": "Tue", "ret": -0.046, "winRate": 48, "volume": 95, "vol": 0.67, "n": 179, "t": -0.92, "edge": 30}, {"key": "Wed", "ret": -0.014, "winRate": 55, "volume": 94, "vol": 0.71, "n": 177, "t": -0.25, "edge": 62}, {"key": "Thu", "ret": 0.152, "winRate": 56, "volume": 86, "vol": 0.83, "n": 179, "t": 2.45, "edge": 88}, {"key": "Fri", "ret": 0.025, "winRate": 50, "volume": 99, "vol": 1.59, "n": 175, "t": 0.21, "edge": 39}], "hour": null, "month": [{"key": "Jan", "ret": 0.059, "winRate": 53, "volume": 100, "vol": 0.7, "n": 74, "t": 0.72, "edge": 68}, {"key": "Feb", "ret": -0.0, "winRate": 56, "volume": 90, "vol": 0.96, "n": 81, "t": -0.0, "edge": 44}, {"key": "Mar", "ret": -0.071, "winRate": 51, "volume": 88, "vol": 0.79, "n": 85, "t": -0.82, "edge": 20}, {"key": "Apr", "ret": -0.054, "winRate": 44, "volume": 93, "vol": 1.1, "n": 79, "t": -0.44, "edge": 18}, {"key": "May", "ret": -0.006, "winRate": 51, "volume": 87, "vol": 0.94, "n": 85, "t": -0.05, "edge": 31}, {"key": "Jun", "ret": 0.02, "winRate": 45, "volume": 97, "vol": 0.66, "n": 85, "t": 0.28, "edge": 44}, {"key": "Jul", "ret": 0.101, "winRate": 66, "volume": 98, "vol": 0.65, "n": 79, "t": 1.39, "edge": 93}, {"key": "Aug", "ret": -0.015, "winRate": 59, "volume": 92, "vol": 0.7, "n": 66, "t": -0.17, "edge": 50}, {"key": "Sep", "ret": -0.019, "winRate": 45, "volume": 87, "vol": 0.58, "n": 64, "t": -0.26, "edge": 23}, {"key": "Oct", "ret": -0.077, "winRate": 49, "volume": 93, "vol": 2.73, "n": 68, "t": -0.23, "edge": 7}, {"key": "Nov", "ret": 0.16, "winRate": 59, "volume": 92, "vol": 0.69, "n": 63, "t": 1.83, "edge": 87}, {"key": "Dec", "ret": -0.011, "winRate": 45, "volume": 95, "vol": 0.56, "n": 56, "t": -0.15, "edge": 35}], "matrix": null, "recommendation": {"verdict": "BUY", "confidence": 59, "bestWindow": {"day": "Thu", "hour": null, "edge": 88}, "worstWindow": {"day": "Mon", "hour": null, "edge": 23}, "earningsSoon": false}}}}