{"instrument": {"id": 18623998, "name": "Millrose Properties", "ticker": "MRP", "kind": "stock", "currency": "USD", "country": "US", "tz": "America/New_York", "slug": "millrose-properties-mrp-xnas", "owners": 82}, "asOf": "2026-06-18", "momentum": {"m3": -2.3, "m12": 13.4}, "daysAxis": ["Mon", "Tue", "Wed", "Thu", "Fri"], "hoursAxis": [], "monthsAxis": ["Jan", "Feb", "Mar", "Apr", "May", "Jun", "Jul", "Aug", "Sep", "Oct", "Nov", "Dec"], "earnings": null, "tf": {"1Y": {"sampleSize": 252, "intradayDays": 0, "weekday": [{"key": "Mon", "ret": -0.256, "winRate": 40, "volume": 100, "vol": 1.48, "n": 48, "t": -1.2, "edge": 25}, {"key": "Tue", "ret": 0.32, "winRate": 62, "volume": 99, "vol": 1.42, "n": 53, "t": 1.64, "edge": 91}, {"key": "Wed", "ret": 0.181, "winRate": 49, "volume": 100, "vol": 2.08, "n": 53, "t": 0.63, "edge": 60}, {"key": "Thu", "ret": -0.115, "winRate": 44, "volume": 99, "vol": 1.62, "n": 48, "t": -0.49, "edge": 22}, {"key": "Fri", "ret": 0.147, "winRate": 48, "volume": 100, "vol": 1.65, "n": 50, "t": 0.63, "edge": 67}], "hour": null, "month": [{"key": "Jan", "ret": 0.129, "winRate": 40, "volume": 97, "vol": 1.66, "n": 20, "t": 0.35, "edge": 39}, {"key": "Feb", "ret": 0.276, "winRate": 63, "volume": 97, "vol": 1.17, "n": 19, "t": 1.03, "edge": 74}, {"key": "Mar", "ret": -0.496, "winRate": 36, "volume": 97, "vol": 1.89, "n": 22, "t": -1.23, "edge": 8}, {"key": "Apr", "ret": 0.573, "winRate": 57, "volume": 95, "vol": 1.37, "n": 21, "t": 1.91, "edge": 70}, {"key": "May", "ret": -0.388, "winRate": 60, "volume": 98, "vol": 2.31, "n": 20, "t": -0.75, "edge": 31}, {"key": "Jun", "ret": 0.18, "winRate": 50, "volume": 98, "vol": 1.65, "n": 22, "t": 0.51, "edge": 55}, {"key": "Jul", "ret": 0.351, "winRate": 55, "volume": 95, "vol": 1.49, "n": 22, "t": 1.11, "edge": 58}, {"key": "Aug", "ret": 0.788, "winRate": 67, "volume": 95, "vol": 1.24, "n": 21, "t": 2.9, "edge": 90}, {"key": "Sep", "ret": -0.227, "winRate": 33, "volume": 95, "vol": 1.24, "n": 21, "t": -0.84, "edge": 18}, {"key": "Oct", "ret": -0.079, "winRate": 43, "volume": 97, "vol": 1.31, "n": 23, "t": -0.29, "edge": 40}, {"key": "Nov", "ret": -0.27, "winRate": 47, "volume": 100, "vol": 2.18, "n": 19, "t": -0.54, "edge": 33}, {"key": "Dec", "ret": -0.073, "winRate": 36, "volume": 99, "vol": 1.78, "n": 22, "t": -0.19, "edge": 33}], "matrix": null, "recommendation": {"verdict": "WAIT", "confidence": 50, "bestWindow": {"day": "Tue", "hour": null, "edge": 91}, "worstWindow": {"day": "Thu", "hour": null, "edge": 22}, "earningsSoon": false}}, "3Y": {"sampleSize": 342, "intradayDays": 0, "weekday": [{"key": "Mon", "ret": -0.394, "winRate": 42, "volume": 100, "vol": 2.3, "n": 65, "t": -1.38, "edge": 17}, {"key": "Tue", "ret": 0.293, "winRate": 56, "volume": 99, "vol": 1.94, "n": 71, "t": 1.27, "edge": 83}, {"key": "Wed", "ret": 0.259, "winRate": 49, "volume": 100, "vol": 2.16, "n": 71, "t": 1.01, "edge": 77}, {"key": "Thu", "ret": 0.04, "winRate": 46, "volume": 99, "vol": 1.92, "n": 67, "t": 0.17, "edge": 45}, {"key": "Fri", "ret": 0.412, "winRate": 51, "volume": 100, "vol": 2.58, "n": 68, "t": 1.32, "edge": 80}], "hour": null, "month": [{"key": "Jan", "ret": 0.129, "winRate": 40, "volume": 97, "vol": 1.66, "n": 20, "t": 0.35, "edge": 39}, {"key": "Feb", "ret": 0.343, "winRate": 60, "volume": 99, "vol": 4.02, "n": 35, "t": 0.51, "edge": 60}, {"key": "Mar", "ret": 0.113, "winRate": 44, "volume": 98, "vol": 2.55, "n": 43, "t": 0.29, "edge": 40}, {"key": "Apr", "ret": 0.204, "winRate": 55, "volume": 95, "vol": 2.12, "n": 42, "t": 0.62, "edge": 46}, {"key": "May", "ret": 0.08, "winRate": 51, "volume": 97, "vol": 2.09, "n": 41, "t": 0.25, "edge": 44}, {"key": "Jun", "ret": 0.062, "winRate": 48, "volume": 95, "vol": 1.41, "n": 33, "t": 0.25, "edge": 38}, {"key": "Jul", "ret": 0.351, "winRate": 55, "volume": 95, "vol": 1.49, "n": 22, "t": 1.11, "edge": 57}, {"key": "Aug", "ret": 0.788, "winRate": 67, "volume": 95, "vol": 1.24, "n": 21, "t": 2.9, "edge": 91}, {"key": "Sep", "ret": -0.227, "winRate": 33, "volume": 95, "vol": 1.24, "n": 21, "t": -0.84, "edge": 11}, {"key": "Oct", "ret": -0.079, "winRate": 43, "volume": 97, "vol": 1.31, "n": 23, "t": -0.29, "edge": 34}, {"key": "Nov", "ret": -0.27, "winRate": 47, "volume": 100, "vol": 2.18, "n": 19, "t": -0.54, "edge": 34}, {"key": "Dec", "ret": -0.073, "winRate": 36, "volume": 99, "vol": 1.78, "n": 22, "t": -0.19, "edge": 32}], "matrix": null, "recommendation": {"verdict": "WAIT", "confidence": 50, "bestWindow": {"day": "Tue", "hour": null, "edge": 83}, "worstWindow": {"day": "Mon", "hour": null, "edge": 17}, "earningsSoon": false}}, "5Y": {"sampleSize": 342, "intradayDays": 0, "weekday": [{"key": "Mon", "ret": -0.394, "winRate": 42, "volume": 100, "vol": 2.3, "n": 65, "t": -1.38, "edge": 17}, {"key": "Tue", "ret": 0.293, "winRate": 56, "volume": 99, "vol": 1.94, "n": 71, "t": 1.27, "edge": 83}, {"key": "Wed", "ret": 0.259, "winRate": 49, "volume": 100, "vol": 2.16, "n": 71, "t": 1.01, "edge": 77}, {"key": "Thu", "ret": 0.04, "winRate": 46, "volume": 99, "vol": 1.92, "n": 67, "t": 0.17, "edge": 45}, {"key": "Fri", "ret": 0.412, "winRate": 51, "volume": 100, "vol": 2.58, "n": 68, "t": 1.32, "edge": 80}], "hour": null, "month": [{"key": "Jan", "ret": 0.129, "winRate": 40, "volume": 97, "vol": 1.66, "n": 20, "t": 0.35, "edge": 39}, {"key": "Feb", "ret": 0.343, "winRate": 60, "volume": 99, "vol": 4.02, "n": 35, "t": 0.51, "edge": 60}, {"key": "Mar", "ret": 0.113, "winRate": 44, "volume": 98, "vol": 2.55, "n": 43, "t": 0.29, "edge": 40}, {"key": "Apr", "ret": 0.204, "winRate": 55, "volume": 95, "vol": 2.12, "n": 42, "t": 0.62, "edge": 46}, {"key": "May", "ret": 0.08, "winRate": 51, "volume": 97, "vol": 2.09, "n": 41, "t": 0.25, "edge": 44}, {"key": "Jun", "ret": 0.062, "winRate": 48, "volume": 95, "vol": 1.41, "n": 33, "t": 0.25, "edge": 38}, {"key": "Jul", "ret": 0.351, "winRate": 55, "volume": 95, "vol": 1.49, "n": 22, "t": 1.11, "edge": 57}, {"key": "Aug", "ret": 0.788, "winRate": 67, "volume": 95, "vol": 1.24, "n": 21, "t": 2.9, "edge": 91}, {"key": "Sep", "ret": -0.227, "winRate": 33, "volume": 95, "vol": 1.24, "n": 21, "t": -0.84, "edge": 11}, {"key": "Oct", "ret": -0.079, "winRate": 43, "volume": 97, "vol": 1.31, "n": 23, "t": -0.29, "edge": 34}, {"key": "Nov", "ret": -0.27, "winRate": 47, "volume": 100, "vol": 2.18, "n": 19, "t": -0.54, "edge": 34}, {"key": "Dec", "ret": -0.073, "winRate": 36, "volume": 99, "vol": 1.78, "n": 22, "t": -0.19, "edge": 32}], "matrix": null, "recommendation": {"verdict": "WAIT", "confidence": 50, "bestWindow": {"day": "Tue", "hour": null, "edge": 83}, "worstWindow": {"day": "Mon", "hour": null, "edge": 17}, "earningsSoon": false}}}}